django_i18n_noprefix/__init__.py
django_i18n_noprefix/__version__.py
django_i18n_noprefix/apps.py
django_i18n_noprefix/middleware.py
django_i18n_noprefix/urls.py
django_i18n_noprefix/utils.py
django_i18n_noprefix/views.py
django_i18n_noprefix/static/i18n_noprefix/css/README.md
django_i18n_noprefix/static/i18n_noprefix/css/bootstrap5.css
django_i18n_noprefix/static/i18n_noprefix/css/tailwind.css
django_i18n_noprefix/static/i18n_noprefix/css/vanilla.css
django_i18n_noprefix/templates/i18n_noprefix/language_selector.html
django_i18n_noprefix/templates/i18n_noprefix/language_selector_inline.html
django_i18n_noprefix/templates/i18n_noprefix/language_selector_list.html
django_i18n_noprefix/templates/i18n_noprefix/examples/bootstrap5_example.html
django_i18n_noprefix/templates/i18n_noprefix/examples/tailwind_example.html
django_i18n_noprefix/templates/i18n_noprefix/examples/vanilla_example.html
django_i18n_noprefix/templatetags/__init__.py
django_i18n_noprefix/templatetags/i18n_noprefix.py
django_i18n_noprefix-0.1.1.dist-info/METADATA
django_i18n_noprefix-0.1.1.dist-info/WHEEL
django_i18n_noprefix-0.1.1.dist-info/licenses/LICENSE
django_i18n_noprefix-0.1.1.dist-info/RECORD
