Metadata-Version: 2.4
Name: django-i18n-noprefix
Version: 0.1.1
Summary: Django internationalization without URL prefixes
Project-URL: Homepage, https://github.com/jinto/django-i18n-noprefix
Project-URL: Documentation, https://github.com/jinto/django-i18n-noprefix#readme
Project-URL: Repository, https://github.com/jinto/django-i18n-noprefix.git
Project-URL: Issues, https://github.com/jinto/django-i18n-noprefix/issues
Project-URL: Changelog, https://github.com/jinto/django-i18n-noprefix/blob/main/CHANGELOG.md
Author: jinto
License: MIT
License-File: LICENSE
Keywords: django,i18n,internationalization,l10n,localization,no-prefix,translation,url
Classifier: Development Status :: 3 - Alpha
Classifier: Environment :: Web Environment
Classifier: Framework :: Django
Classifier: Framework :: Django :: 4.2
Classifier: Framework :: Django :: 5.0
Classifier: Framework :: Django :: 5.1
Classifier: Framework :: Django :: 5.2
Classifier: Intended Audience :: Developers
Classifier: License :: OSI Approved :: MIT License
Classifier: Operating System :: OS Independent
Classifier: Programming Language :: Python
Classifier: Programming Language :: Python :: 3
Classifier: Programming Language :: Python :: 3.8
Classifier: Programming Language :: Python :: 3.9
Classifier: Programming Language :: Python :: 3.10
Classifier: Programming Language :: Python :: 3.11
Classifier: Programming Language :: Python :: 3.12
Classifier: Topic :: Internet :: WWW/HTTP
Classifier: Topic :: Software Development :: Internationalization
Classifier: Topic :: Software Development :: Libraries :: Python Modules
Requires-Python: >=3.8
Requires-Dist: django>=4.2
Requires-Dist: twine>=6.1.0
Provides-Extra: dev
Requires-Dist: black>=23.0.0; extra == 'dev'
Requires-Dist: django-stubs>=4.2.0; extra == 'dev'
Requires-Dist: mypy>=1.0.0; extra == 'dev'
Requires-Dist: pre-commit>=3.5.0; extra == 'dev'
Requires-Dist: pytest-cov>=4.0.0; extra == 'dev'
Requires-Dist: pytest-django>=4.5.0; extra == 'dev'
Requires-Dist: pytest>=7.0.0; extra == 'dev'
Requires-Dist: ruff>=0.1.0; extra == 'dev'
Requires-Dist: tox>=4.0.0; extra == 'dev'
